giftwrapy/__init__.py
giftwrapy/giftwrapy.py
giftwrapy-0.3.0.dist-info/METADATA
giftwrapy-0.3.0.dist-info/WHEEL
giftwrapy-0.3.0.dist-info/entry_points.txt
giftwrapy-0.3.0.dist-info/licenses/LICENSE
giftwrapy-0.3.0.dist-info/RECORD
