Metadata-Version: 2.3
Name: giftwrapy
Version: 0.3.0
Summary: A tool to convert a project/folder/repo into one long markdown file for use with AI assistants
Project-URL: Homepage, https://github.com/jacksonrgwalker/giftwrapy
Author-email: Jackson Walker <jacksonrgwalker@gmail.com>
License-File: LICENSE
Classifier: License :: OSI Approved :: MIT License
Classifier: Operating System :: OS Independent
Classifier: Programming Language :: Python :: 3
Requires-Python: >=3.9
